httpdogs/__init__.py
httpdogs-1.0.0.dist-info/LICENSE
httpdogs-1.0.0.dist-info/METADATA
httpdogs-1.0.0.dist-info/WHEEL
httpdogs-1.0.0.dist-info/top_level.txt
httpdogs-1.0.0.dist-info/RECORD
