Metadata-Version: 2.1
Name: httpdogs
Version: 1.0.0
Summary: Bringing you closer to your favorite HTTP Dogs.
Home-page: https://github.com/itsmewulf/httpdogs
Author: itsmewulf
Author-email: wulf.developer@gmail.com
License: UNKNOWN
Keywords: dog,http,request,api,wrapper
Platform: UNKNOWN
Classifier: Programming Language :: Python :: 3
Classifier: License :: OSI Approved :: MIT License
Classifier: Operating System :: OS Independent
Requires-Python: >=3.6
